<MotionLabeling author="Hilde Kuehne" motionFile="P49\P49_friedegg.fine" motionFilePathType="first parent" motionFileType=".avi" motionSequenceName="P49" segType="Manual Multi Segmentation" segmentationCriteria="MotionSequenceLabel_ADLDataset_17_12_2010_h.xml"> 
<Limb name="whole_body"> 
<MotionLabel name="garbage" startPoint="1" endPoint="15"/> 
<MotionLabel name="reach_butter" startPoint="16" endPoint="46"/> 
<MotionLabel name="liftopen_lidButter" startPoint="47" endPoint="67"/> 
<MotionLabel name="carry_butter" startPoint="68" endPoint="73"/> 
<MotionLabel name="reach_butter" startPoint="74" endPoint="81"/> 
<MotionLabel name="reach_knife" startPoint="82" endPoint="88"/> 
<MotionLabel name="carry_butter" startPoint="89" endPoint="126"/> 
<MotionLabel name="reach_knife" startPoint="127" endPoint="145"/> 
<MotionLabel name="transfer_butter2pan" startPoint="146" endPoint="165"/> 
<MotionLabel name="reach_butter" startPoint="166" endPoint="177"/> 
<MotionLabel name="carry_butter" startPoint="178" endPoint="199"/> 
<MotionLabel name="reach_knife" startPoint="200" endPoint="209"/> 
<MotionLabel name="transfer_butter2pan" startPoint="210" endPoint="228"/> 
<MotionLabel name="reach_knife" startPoint="229" endPoint="248"/> 
<MotionLabel name="carry_knife" startPoint="249" endPoint="260"/> 
<MotionLabel name="reach_butter" startPoint="261" endPoint="276"/> 
<MotionLabel name="carry_butter" startPoint="277" endPoint="361"/> 
<MotionLabel name="reach_spatula" startPoint="362" endPoint="411"/> 
<MotionLabel name="reach_handle" startPoint="412" endPoint="424"/> 
<MotionLabel name="carry_spatula" startPoint="425" endPoint="500"/> 
<MotionLabel name="reach_eggcarton" startPoint="501" endPoint="541"/> 
<MotionLabel name="liftopen_eggcarton" startPoint="542" endPoint="554"/> 
<MotionLabel name="reach_egg" startPoint="555" endPoint="563"/> 
<MotionLabel name="pressclose_eggcarton" startPoint="564" endPoint="592"/> 
<MotionLabel name="reach_handle" startPoint="593" endPoint="610"/> 
<MotionLabel name="crack_egg" startPoint="611" endPoint="636"/> 
<MotionLabel name="transfer_egg2pan" startPoint="637" endPoint="655"/> 
<MotionLabel name="carry_egg" startPoint="656" endPoint="728"/> 
<MotionLabel name="reach_handle" startPoint="729" endPoint="754"/> 
<MotionLabel name="carry_handle" startPoint="755" endPoint="829"/> 
<MotionLabel name="turnonOff_stove" startPoint="830" endPoint="883"/> 
<MotionLabel name="reach_handle" startPoint="884" endPoint="911"/> 
<MotionLabel name="fry_egg" startPoint="912" endPoint="972"/> 
<MotionLabel name="move" startPoint="973" endPoint="984"/> 
<MotionLabel name="garbage" startPoint="985" endPoint="1840"/> 
<MotionLabel name="turnonOff_stove" startPoint="1841" endPoint="1878"/> 
<MotionLabel name="reach_spatula" startPoint="1879" endPoint="1900"/> 
<MotionLabel name="reach_handle" startPoint="1901" endPoint="1915"/> 
<MotionLabel name="fry_egg" startPoint="1916" endPoint="2581"/> 
<MotionLabel name="move" startPoint="2582" endPoint="2599"/> 
<MotionLabel name="garbage" startPoint="2600" endPoint="2960"/> 
<MotionLabel name="reach_spatula" startPoint="2961" endPoint="2968"/> 
<MotionLabel name="carry_spatula" startPoint="2969" endPoint="2998"/> 
<MotionLabel name="fry_egg" startPoint="2999" endPoint="3207"/> 
<MotionLabel name="carry_spatula" startPoint="3208" endPoint="3533"/> 
<MotionLabel name="fry_egg" startPoint="3534" endPoint="3841"/> 
<MotionLabel name="carry_spatula" startPoint="3842" endPoint="3883"/> 
<MotionLabel name="fry_egg" startPoint="3884" endPoint="3962"/> 
<MotionLabel name="carry_spatula" startPoint="3963" endPoint="4010"/> 
<MotionLabel name="fry_egg" startPoint="4011" endPoint="4427"/> 
<MotionLabel name="carry_spatula" startPoint="4428" endPoint="4441"/> 
<MotionLabel name="move" startPoint="4442" endPoint="4451"/> 
<MotionLabel name="reach_stove" startPoint="4452" endPoint="4467"/> 
<MotionLabel name="turnonOff_stove" startPoint="4468" endPoint="4532"/> 
<MotionLabel name="reach_spatula" startPoint="4533" endPoint="4562"/> 
<MotionLabel name="carry_spatula" startPoint="4563" endPoint="4580"/> 
<MotionLabel name="fry_egg" startPoint="4581" endPoint="5018"/> 
<MotionLabel name="reach_stove" startPoint="5019" endPoint="5032"/> 
<MotionLabel name="turnonOff_stove" startPoint="5033" endPoint="5082"/> 
<MotionLabel name="reach_spatula" startPoint="5083" endPoint="5094"/> 
<MotionLabel name="fry_egg" startPoint="5095" endPoint="5114"/> 
<MotionLabel name="garbage" startPoint="5115" endPoint="5178"/> 
</Limb> 
</MotionLabeling> 
