<MotionLabeling author="Hilde Kuehne" motionFile="P54\P54_friedegg.fine" motionFilePathType="first parent" motionFileType=".avi" motionSequenceName="P54" segType="Manual Multi Segmentation" segmentationCriteria="MotionSequenceLabel_ADLDataset_17_12_2010_h.xml"> 
<Limb name="whole_body"> 
<MotionLabel name="garbage" startPoint="1" endPoint="2"/> 
<MotionLabel name="reach_handle" startPoint="3" endPoint="7"/> 
<MotionLabel name="carry_handle" startPoint="8" endPoint="57"/> 
<MotionLabel name="reach_eggcarton" startPoint="58" endPoint="68"/> 
<MotionLabel name="liftopen_eggcarton" startPoint="69" endPoint="74"/> 
<MotionLabel name="reach_egg" startPoint="75" endPoint="108"/> 
<MotionLabel name="carry_egg" startPoint="109" endPoint="122"/> 
<MotionLabel name="reach_knife" startPoint="123" endPoint="138"/> 
<MotionLabel name="carry_knife" startPoint="139" endPoint="205"/> 
<MotionLabel name="carry_egg" startPoint="206" endPoint="225"/> 
<MotionLabel name="reach_egg" startPoint="226" endPoint="235"/> 
<MotionLabel name="transfer_egg2pan" startPoint="236" endPoint="283"/> 
<MotionLabel name="carry_egg" startPoint="284" endPoint="292"/> 
<MotionLabel name="reach_handle" startPoint="293" endPoint="302"/> 
<MotionLabel name="carry_handle" startPoint="303" endPoint="307"/> 
<MotionLabel name="fry_egg" startPoint="308" endPoint="342"/> 
<MotionLabel name="reach_salt" startPoint="343" endPoint="369"/> 
<MotionLabel name="carry_salt" startPoint="370" endPoint="374"/> 
<MotionLabel name="pour_salt" startPoint="375" endPoint="404"/> 
<MotionLabel name="reach_salt" startPoint="405" endPoint="409"/> 
<MotionLabel name="carry_salt" startPoint="410" endPoint="424"/> 
<MotionLabel name="reach_pepper" startPoint="425" endPoint="440"/> 
<MotionLabel name="grind_pepper" startPoint="441" endPoint="652"/> 
<MotionLabel name="carry_pepper" startPoint="653" endPoint="678"/> 
<MotionLabel name="reach_salt" startPoint="679" endPoint="695"/> 
<MotionLabel name="carry_salt" startPoint="696" endPoint="701"/> 
<MotionLabel name="pour_salt" startPoint="702" endPoint="723"/> 
<MotionLabel name="reach_salt" startPoint="724" endPoint="727"/> 
<MotionLabel name="carry_salt" startPoint="728" endPoint="737"/> 
<MotionLabel name="reach_cabinet" startPoint="738" endPoint="760"/> 
<MotionLabel name="open_cabinet" startPoint="761" endPoint="790"/> 
<MotionLabel name="close_cabinet" startPoint="791" endPoint="817"/> 
<MotionLabel name="move" startPoint="818" endPoint="839"/> 
<MotionLabel name="fry_egg" startPoint="840" endPoint="1400"/> 
<MotionLabel name="pickup_egg" startPoint="1402" endPoint="1465"/> 
<MotionLabel name="carry_spatula" startPoint="1466" endPoint="1494"/> 
<MotionLabel name="carry_handle" startPoint="1495" endPoint="1526"/> 
<MotionLabel name="reach_plate" startPoint="1527" endPoint="1553"/> 
<MotionLabel name="garbage" startPoint="1554" endPoint="1559"/> 
</Limb> 
</MotionLabeling> 
